[{"content_summary": "\n      说起体态问题，其实不止普通人会有，很多明星也是难以避免的，最典型的当然是用下面这三位女神进行对比了！！ 从左至右：如白天鹅般挺拔好气质的刘诗诗、含胸驼背的杨幂、溜肩的神仙姐姐...\n    ", "like": " 1", "title": "再这么下去，你的“乌龟颈”会比杨幂还严重！", "read": " 53\n", "money": 0, "content_figure_url": "//upload-images.jianshu.io/upload_images/10116806-f970d019f5e009d3?imageMogr2/auto-orient/strip|imageView2/1/w/150/h/120", "content_url": "/p/4afa069c79df", "createTime": "2018-05-25T08:59:44+08:00", "comments": " 0\n", "_id": "note-28564490", "nickname": "", "author_icon_url": "//upload.jianshu.io/users/upload_avatars/10116806/0e232a7a-addd-4169-b065-0a47aefb9048.jpg?imageMogr2/auto-orient/strip|imageView2/1/w/64/h/64"},{"content_summary": "\n      文/曾高飞    巨头之争，城门失火，殃及池鱼。虽然都姓马，五百年前是一家，但阿里与腾讯，立场之鲜明，竞争之激烈，怨恨之深刻，估计前无古人，后无来者。阿里发明的排他性“二选一...\n    ", "like": " 0", "title": "从品牌封锁到资本封锁 阿里打击腾讯殃及池鱼", "read": " 30\n", "money": 0, "content_figure_url": "//upload-images.jianshu.io/upload_images/10137120-535dd421a3089065?imageMogr2/auto-orient/strip|imageView2/1/w/150/h/120", "content_url": "/p/c8a9e6d696e4", "createTime": "2018-05-25T08:15:01+08:00", "comments": " 1\n", "_id": "note-28563273", "nickname": "", "author_icon_url": "//upload.jianshu.io/users/upload_avatars/10137120/68726643-2508-4877-9c10-074eebf5cb94.png?imageMogr2/auto-orient/strip|imageView2/1/w/64/h/64"},{"content_summary": "\n      出门在外的游子最牵挂的是在家的爸爸、妈妈，为了更好的与父母联络，我们需给父母购买一台父母称心如意的手机，但市面上几乎都是为年轻人定制的手机，没有几款真正适合老人使用的手机，作...\n    ", "like": " 0", "title": "全球首款采用镀金工艺的手机，比诺基亚还强悍的全网通功能手机", "read": " 17\n", "money": 0, "content_figure_url": "//upload-images.jianshu.io/upload_images/4074907-ecb9888a637ca368?imageMogr2/auto-orient/strip|imageView2/1/w/150/h/120", "content_url": "/p/1e320f7db0e3", "createTime": "2018-05-25T07:32:15+08:00", "comments": " 0\n", "_id": "note-28562280", "nickname": "", "author_icon_url": "//upload.jianshu.io/users/upload_avatars/4074907/80fae038ccc1.jpg?imageMogr2/auto-orient/strip|imageView2/1/w/64/h/64"},{"content_summary": "\n      互联网公司存在的价值在于用自己的产品为自己创造利润和生存空间。而产品是互联网公司的核心环节，一个好的产品是生成的基础和关键，那么如何开发出好的产品就必然涉及到产品定位和需求管...\n    ", "like": " 0", "title": "产品新人如何进行需求管理", "read": " 26\n", "money": 0, "content_figure_url": "//upload-images.jianshu.io/upload_images/1341843-35663660388fb244.png?imageMogr2/auto-orient/strip|imageView2/1/w/150/h/120", "content_url": "/p/76c6f95f9d2c", "createTime": "2018-05-25T07:14:39+08:00", "comments": " 0\n", "_id": "note-28554876", "nickname": "", "author_icon_url": "//upload.jianshu.io/users/upload_avatars/1341843/d51dfc35-8078-46f1-b7d8-9f5af6360741.jpg?imageMogr2/auto-orient/strip|imageView2/1/w/64/h/64"},{"content_summary": "\n      这已经不是一个秘密，只是很少有人知道：市面上并不缺乏真正行动起来布局并利用区块链的上市公司。甚至在中国，这都不是少数。于是，已经成功发行了全球首支区块链 ETF 基金的资产管...\n    ", "like": " 0", "title": "这家美国资管公司要在纳斯达克发行 ETF 追踪中国区块链上市公司，他们凭什么？", "read": " 12\n", "money": 0, "content_figure_url": "//upload-images.jianshu.io/upload_images/9354614-2367ae7e5642459f.jpg?imageMogr2/auto-orient/strip|imageView2/1/w/150/h/120", "content_url": "/p/b9de8e32ec24", "createTime": "2018-05-22T14:47:55+08:00", "comments": " 0\n", "_id": "note-28434288", "nickname": "", "author_icon_url": "//upload.jianshu.io/users/upload_avatars/9354614/db2b1b3e-4532-4dd6-bf40-c530515989f3.png?imageMogr2/auto-orient/strip|imageView2/1/w/64/h/64"},{"content_summary": "\n      ​引言 本文是 TalkingData 首席数据科学家张夏天翻译自 Highly Scalable Blog的一篇文章，介绍了零售业中的数据挖掘问题。 本文内容包括零售业中的...\n    ", "like": " 0", "title": "万字长文，细数零售业中的那些数据挖掘问题（下）", "read": " 8\n", "money": 0, "content_figure_url": "//upload-images.jianshu.io/upload_images/5834515-879d713867b0ff02?imageMogr2/auto-orient/strip|imageView2/1/w/150/h/120", "content_url": "/p/c1f97f1ee730", "createTime": "2018-05-22T15:42:06+08:00", "comments": " 0\n", "_id": "note-28437001", "nickname": "", "author_icon_url": "//upload.jianshu.io/users/upload_avatars/5834515/d4c53a18-4a1d-48c0-a195-3a33d2ec696f?imageMogr2/auto-orient/strip|imageView2/1/w/64/h/64"},{"content_summary": "\n      一、为什么要建立用户成长体系 用户成长体系又叫用户激励系统，是指通过数值化用户行为，累加求和后作为用户对平台忠诚度、贡献度的衡量依据，同时可以刺激用户留在平台的一套结构。核心...\n    ", "like": " 0", "title": "从0-1建立用户成长体系的几点思考", "read": " 17\n", "money": 0, "content_figure_url": "//upload-images.jianshu.io/upload_images/6280868-8b2a806b893f4d8c.jpg?imageMogr2/auto-orient/strip|imageView2/1/w/150/h/120", "content_url": "/p/2b398d9418e2", "createTime": "2018-05-22T15:41:53+08:00", "comments": " 0\n", "_id": "note-28433829", "nickname": "", "author_icon_url": "//upload.jianshu.io/users/upload_avatars/6280868/8d8952bd-d975-490d-98bb-d98fefa90391.jpg?imageMogr2/auto-orient/strip|imageView2/1/w/64/h/64"},{"content_summary": "\n      2018年4月24日，FRESCO和Elastos宣布全球战略合作伙伴关系。FRESCO作为全球首个区块链艺术数字资产网络，将成为Elastos 生态系统上首批DApp之一。...\n    ", "like": " 0", "title": "FRESCO与亦来云达成全球战略合作，共同促进艺术区块链数字资产化", "read": " 7\n", "money": 0, "content_figure_url": "//upload-images.jianshu.io/upload_images/1178255-6a6b02be4f454eea.png?imageMogr2/auto-orient/strip|imageView2/1/w/150/h/120", "content_url": "/p/8ecababd3203", "createTime": "2018-05-24T12:17:45+08:00", "comments": " 0\n", "_id": "note-28524301", "nickname": "", "author_icon_url": "//upload.jianshu.io/users/upload_avatars/1178255/3b92f3d6-9809-415a-a6eb-bee46c3daecf.jpg?imageMogr2/auto-orient/strip|imageView2/1/w/64/h/64"},{"content_summary": "\n      2018-05-11 发布者：猎隼 浏览次数：148次 在虎投财经与武汉猎隼科技CEO王志鹏的采访中，他首先就纠正了一个概念： 『‘无人机行业’其实是个伪命题，应该说无人机应...\n    ", "like": " 0", "title": "2018-05-24猎隼科技：专业无人机为行业赋能，AI技术对标Intel", "read": " 8\n", "money": 0, "content_figure_url": "//upload-images.jianshu.io/upload_images/12341693-d9ac030f63bd1975.jpg?imageMogr2/auto-orient/strip|imageView2/1/w/150/h/120", "content_url": "/p/19d589ea9274", "createTime": "2018-05-24T14:46:07+08:00", "comments": " 0\n", "_id": "note-28531517", "nickname": "", "author_icon_url": "//upload.jianshu.io/users/upload_avatars/12341693/3b0aaa35-acfd-45ca-9844-7fb0edfb52cc.jpg?imageMogr2/auto-orient/strip|imageView2/1/w/64/h/64"},{"content_summary": "\n      几年来，OnePlus一直在发布具有相同承诺变体的手机：获得所有最好的旗舰智能手机功能，无需支付旗舰价格。结合一些精明的市场营销，该战略创造了一批忠实的粉丝。而且这些粉丝也不...\n    ", "like": " 0", "title": "ONEPLUS 6评论：新手机，同样的妥协", "read": " 9\n", "money": 0, "content_figure_url": "//upload-images.jianshu.io/upload_images/458228-0949b2c5de0f6c4f.jpg?imageMogr2/auto-orient/strip|imageView2/1/w/150/h/120", "content_url": "/p/e5437427381d", "createTime": "2018-05-24T13:58:18+08:00", "comments": " 0\n", "_id": "note-28529151", "nickname": "", "author_icon_url": "//upload.jianshu.io/users/upload_avatars/458228/253fa20d-b99d-4385-850b-4ee72cee27b5.jpg?imageMogr2/auto-orient/strip|imageView2/1/w/64/h/64"},{"content_summary": "\n      RNG击败韩国KZ，夺得英雄联盟季中赛冠军的消息余热未散，中国电竞迎来“黄金时代”的声音如日中天，似乎超越隔壁的“电竞之国”韩国已经不在话下。 但说实话，战绩虽然很重要，不过...\n    ", "like": " 0", "title": "【授权转载】一项国技的缘起与陨落", "read": " 19\n", "money": 0, "content_figure_url": "//upload-images.jianshu.io/upload_images/10272773-8dc895ab8daca69e?imageMogr2/auto-orient/strip|imageView2/1/w/150/h/120", "content_url": "/p/595176c10cc9", "createTime": "2018-05-24T13:02:43+08:00", "comments": " 0\n", "_id": "note-28527179", "nickname": "", "author_icon_url": "//upload.jianshu.io/users/upload_avatars/10272773/eb9d5e91-8eb8-4e75-94a8-57dc19333946.jpg?imageMogr2/auto-orient/strip|imageView2/1/w/64/h/64"},{"content_summary": "\n      日新月异，时代在变化。人们总是习惯用以前的思维，来思考现在的东西。经常会出现一种情况：想不明白。“爆品战略”，以前的商家，要做出一款爆款产品比的是谁有钱，谁投了更多的广告。从...\n    ", "like": " 0", "title": "《爆品战略》：普通产品和爆品，相差只有1%", "read": " 65\n", "money": 0, "content_figure_url": "//upload-images.jianshu.io/upload_images/9956098-ca06af8cc11bd465?imageMogr2/auto-orient/strip|imageView2/1/w/150/h/120", "content_url": "/p/443af45c593f", "createTime": "2018-05-22T17:00:03+08:00", "comments": " 2\n", "_id": "note-28438217", "nickname": "", "author_icon_url": "//upload.jianshu.io/users/upload_avatars/9956098/75300e0c-cb9b-4b0f-982b-fd76bf2ce088.jpg?imageMogr2/auto-orient/strip|imageView2/1/w/64/h/64"},{"content_summary": "\n      自从荣耀作为单独的互联网品牌独立出来之后，无论是它的外在还是内在表现，相比以往可以说有着质的提升，这一点更是从它市场份额的增长有所体现。今年3月，伴随着荣耀畅玩7C的发布和一...\n    ", "like": " 0", "title": "荣耀畅玩7C使用俩月有感，出乎意料的双摄表现", "read": " 11\n", "money": 0, "content_figure_url": "//upload-images.jianshu.io/upload_images/4074907-06022aaa611f627c?imageMogr2/auto-orient/strip|imageView2/1/w/150/h/120", "content_url": "/p/70511f54ecc6", "createTime": "2018-05-22T17:14:54+08:00", "comments": " 0\n", "_id": "note-28442354", "nickname": "", "author_icon_url": "//upload.jianshu.io/users/upload_avatars/4074907/80fae038ccc1.jpg?imageMogr2/auto-orient/strip|imageView2/1/w/64/h/64"},{"content_summary": "\n      如何让技术找到落地场景，一直是各大科技公司在不断探索的事情。比如有些科技公司就借人工智能这一波浪潮，瞅准了儿童玩具市场，推出儿童机器人。在这样一个细分市场中，入局的不仅有老牌...\n    ", "like": " 3", "title": "儿童故事机、机器人的真实体验和用户场景解读", "read": " 52\n", "money": 0, "content_figure_url": "//upload-images.jianshu.io/upload_images/12286264-cb93061cd87328f4?imageMogr2/auto-orient/strip|imageView2/1/w/150/h/120", "content_url": "/p/5f15d5fdceb2", "createTime": "2018-05-22T16:48:29+08:00", "comments": " 2\n", "_id": "note-28440881", "nickname": "", "author_icon_url": "//upload.jianshu.io/users/upload_avatars/12286264/375edb54-79e1-4584-8943-d2c39a2e6a08.jpg?imageMogr2/auto-orient/strip|imageView2/1/w/64/h/64"},{"content_summary": "\n      国内新闻 1. 百度推出智能小程序 七月正式上线 在百度联盟峰会上度 App 业务部总经理平晓黎首次证实：百度确实要做小程序，名称为「百度智能小程序」，预计在今年 7 月正式...\n    ", "like": " 1", "title": "百度7月推出智能小程序；美图宣布自6月起转型社交平台", "read": " 38\n", "money": 0, "content_figure_url": "//upload-images.jianshu.io/upload_images/12286264-858409e7827bd6e8?imageMogr2/auto-orient/strip|imageView2/1/w/150/h/120", "content_url": "/p/09483d04f5f4", "createTime": "2018-05-23T13:18:54+08:00", "comments": " 0\n", "_id": "note-28479223", "nickname": "", "author_icon_url": "//upload.jianshu.io/users/upload_avatars/12286264/375edb54-79e1-4584-8943-d2c39a2e6a08.jpg?imageMogr2/auto-orient/strip|imageView2/1/w/64/h/64"},{"content_summary": "\n      随着发布日期的临近，小米8的信息越来越多，也越来越接近真相。刘海屏+窄下巴设计，将是小米8在外观设计上的最大看点，当然，小米8还会带来一些黑科技，比如屏幕指纹识别技术、3D结...\n    ", "like": " 0", "title": "小米8即将发布，这样的旗舰雷军就不担心吗？", "read": " 20\n", "money": 0, "content_figure_url": "", "content_url": "/p/e3a0aefd5568", "createTime": "2018-05-24T12:24:40+08:00", "comments": " 0\n", "_id": "note-28526078", "nickname": "", "author_icon_url": "//upload.jianshu.io/users/upload_avatars/9085281/9de3892c-d0ee-48b7-8273-2715de4b73ba.png?imageMogr2/auto-orient/strip|imageView2/1/w/64/h/64"},{"content_summary": "\n      2018年1月17日由MYLES SNIDER@ Multicoin Capital提供，翻译by Effe 自从我参与加密网络以来，稳定代币一直是我的主要兴趣领域之一。20...\n    ", "like": " 0", "title": "稳定代币概述", "read": " 6\n", "money": 0, "content_figure_url": "", "content_url": "/p/b2a164e63501", "createTime": "2018-05-24T10:36:33+08:00", "comments": " 0\n", "_id": "note-28521368", "nickname": "", "author_icon_url": "//upload.jianshu.io/users/upload_avatars/12317498/0640f636-e655-4233-b832-08cb189a5c85?imageMogr2/auto-orient/strip|imageView2/1/w/64/h/64"},{"content_summary": "\n      基于人工智能的教育，会让孩子更有效更快速的先把传统的科目快速学好，从而让学生有更多的时候培养自己不会被人工智能取代的技能。 “那是什么呢？其实就是两种，一是创意，一是人与人之...\n    ", "like": " 0", "title": "李开复、俞敏洪纵论AI教育：“人工智能利好高考；未来的老师最难当”", "read": " 8\n", "money": 0, "content_figure_url": "//upload-images.jianshu.io/upload_images/11747081-ca34a2d660e7bad1?imageMogr2/auto-orient/strip|imageView2/1/w/150/h/120", "content_url": "/p/6e59a67aaed0", "createTime": "2018-05-24T14:16:24+08:00", "comments": " 0\n", "_id": "note-28529939", "nickname": "", "author_icon_url": "//upload.jianshu.io/users/upload_avatars/11747081/36d37171-ccab-4fc5-b4a8-f8fd89e413b9.jpg?imageMogr2/auto-orient/strip|imageView2/1/w/64/h/64"},{"content_summary": "\n      近日，意甲收官战引起广泛关注，国际米兰在客场3:2逆转拉齐奥，时隔六年重返欧冠，其中，最为欣喜若狂的应当数大股东苏宁集团。 “苏宁品牌+体育”模式，让苏宁叩开欧洲市场大门 尽...\n    ", "like": " 0", "title": "苏宁当年不被看好的投资，如今收到成倍的回报！", "read": " 8\n", "money": 0, "content_figure_url": "//upload-images.jianshu.io/upload_images/5227845-972fee38aebeac5b.jpg?imageMogr2/auto-orient/strip|imageView2/1/w/150/h/120", "content_url": "/p/c4f94e400066", "createTime": "2018-05-24T14:21:53+08:00", "comments": " 0\n", "_id": "note-28529855", "nickname": "", "author_icon_url": "//upload.jianshu.io/users/upload_avatars/5227845/aaec28a0-a44e-4990-9363-4cd6cbca1d79.jpg?imageMogr2/auto-orient/strip|imageView2/1/w/64/h/64"},{"content_summary": "\n      2016年1月，盒马鲜生在上海浦东金桥开出全国第一家门店，其独有的线上线下一体化模式，以及对零售业“人、货、场”的重构，获得业内外人士的一致认可，被称作“新零售标杆”。不过2...\n    ", "like": " 0", "title": "支付宝玩转新零售模式，未来药店开启医药新零售时代", "read": " 6\n", "money": 0, "content_figure_url": "//upload-images.jianshu.io/upload_images/11718300-bfcfc2515cbbdd90.jpg?imageMogr2/auto-orient/strip|imageView2/1/w/150/h/120", "content_url": "/p/7a7b6f38d61e", "createTime": "2018-05-24T23:31:05+08:00", "comments": " 0\n", "_id": "note-28556101", "nickname": "", "author_icon_url": "//upload.jianshu.io/users/upload_avatars/11718300/68b55f95-956e-43f2-880f-0057ab64c104.jpg?imageMogr2/auto-orient/strip|imageView2/1/w/64/h/64"}]